.gitignore
LICENSE
MANIFEST.in
README.md
mearth-filter.txt
setup.py
starspot_backlights.egg-info/PKG-INFO
starspot_backlights.egg-info/SOURCES.txt
starspot_backlights.egg-info/dependency_links.txt
starspot_backlights.egg-info/not-zip-safe
starspot_backlights.egg-info/requires.txt
starspot_backlights.egg-info/top_level.txt
starspotbacklights/__init__.py
starspotbacklights/backlight.py
starspotbacklights/filter.py
starspotbacklights/imports.py
starspotbacklights/version.py
starspotbacklights/data/mearth-filter.txt
starspotbacklights/tests/test_backlight.py
starspotbacklights/tests/test_helpers.py